alaya_cpp_module.cpython-310-x86_64-linux-gnu.so
AlayaDB-1.4.6.dist-info/top_level.txt
AlayaDB-1.4.6.dist-info/RECORD
AlayaDB-1.4.6.dist-info/LICENSE
AlayaDB-1.4.6.dist-info/METADATA
AlayaDB-1.4.6.dist-info/WHEEL
AlayaDB.libs/libgomp-83e84f24.so.1.0.0
AlayaDB/AlayaDB.py
AlayaDB/__init__.py
AlayaDataset/AlayaDataset.py
AlayaDataset/__init__.py
