Metadata-Version: 2.1
Name: AlayaDB
Version: 1.4.6
Summary: AlayaDB
Author: DBGroup@SUSTech
Requires-Python: >=3.8
License-File: LICENSE
Requires-Dist: tqdm
Requires-Dist: numpy==1.24.2
Requires-Dist: h5py==3.8.0
Requires-Dist: scikit-learn
Requires-Dist: h5py
